{
    "homepage": "http://qpdf.sourceforge.net/",
    "version": "9.0.0",
    "license": "Apache-2.0",
    "architecture": {
        "64bit": {
            "url": "https://github.com/qpdf/qpdf/releases/download/release-qpdf-9.0.0/qpdf-9.0.0-bin-msvc64.zip",
            "hash": "b19f048f32f858e51692ecce5b11b3a29d9db57a59efa60fd21fa385e287315c"
        }
    },
    "extract_dir": "qpdf-9.0.0",
    "bin": "bin\\qpdf.exe",
    "checkver": {
        "github": "https://github.com/qpdf/qpdf",
        "re": "qpdf-([\\d.]+)-"
    },
    "autoupdate": {
        "architecture": {
            "64bit": {
                "url": "https://github.com/qpdf/qpdf/releases/download/release-qpdf-$version/qpdf-$version-bin-msvc64.zip"
            }
        },
        "extract_dir": "qpdf-$version"
    }
}
